ovos_solver_pandorabots_plugin/__init__.py
ovos_solver_pandorabots_plugin/version.py
ovos_solver_pandorabots_plugin-0.0.0.dist-info/LICENSE
ovos_solver_pandorabots_plugin-0.0.0.dist-info/METADATA
ovos_solver_pandorabots_plugin-0.0.0.dist-info/WHEEL
ovos_solver_pandorabots_plugin-0.0.0.dist-info/entry_points.txt
ovos_solver_pandorabots_plugin-0.0.0.dist-info/top_level.txt
ovos_solver_pandorabots_plugin-0.0.0.dist-info/zip-safe
ovos_solver_pandorabots_plugin-0.0.0.dist-info/RECORD
